docs_src/conf.py
docs_src/generatePages.py
psychopy_whisper/__init__.py
psychopy_whisper/transcribe.py
psychopy_whisper/components/__init__.py
psychopy_whisper/components/whisperBackend.py
psychopy_whisper-0.0.7.dist-info/licenses/LICENSE
tests/__init__.py
tests/test_transcribe.py
tests/test_components/__init__.py
tests/test_components/test_whisperBackend.py
psychopy_whisper-0.0.7.dist-info/METADATA
psychopy_whisper-0.0.7.dist-info/WHEEL
psychopy_whisper-0.0.7.dist-info/entry_points.txt
psychopy_whisper-0.0.7.dist-info/top_level.txt
psychopy_whisper-0.0.7.dist-info/RECORD
